cve_searchsploit/__init__.py
cve_searchsploit/__main__.py
cve_searchsploit/exploitdb_mapping.json
cve_searchsploit/exploitdb_mapping_cve.json
cve_searchsploit/main.py
cve_searchsploit-1.6.dist-info/DESCRIPTION.rst
cve_searchsploit-1.6.dist-info/METADATA
cve_searchsploit-1.6.dist-info/RECORD
cve_searchsploit-1.6.dist-info/WHEEL
cve_searchsploit-1.6.dist-info/entry_points.txt
cve_searchsploit-1.6.dist-info/metadata.json
cve_searchsploit-1.6.dist-info/top_level.txt
