Metadata-Version: 1.1
Name: cve_searchsploit
Version: 1.6
Summary: Search an exploit in the local exploitdb database by its CVE
Home-page: https://github.com/andreafioraldi/cve_searchsploit
Author: Andrea Fioraldi
Author-email: andreafioraldi@gmail.com
License: MIT
Download-URL: https://github.com/andreafioraldi/cve_searchsploit/archive/master.tar.gz
Platform: UNKNOWN
